toktak_config_fetcher/__init__.py
toktak_config_fetcher/config_utils.py
toktak_config_fetcher-1.0.0.dist-info/METADATA
toktak_config_fetcher-1.0.0.dist-info/WHEEL
toktak_config_fetcher-1.0.0.dist-info/top_level.txt
toktak_config_fetcher-1.0.0.dist-info/RECORD
