Metadata-Version: 2.4
Name: toktak-config-fetcher
Version: 1.0.0
Summary: Config utility library to fetch configuration from AWS SSM/Secrets Manager and .env files
Author-email: Toktak <g9@ggook.com>
Project-URL: Homepage, https://gitlab.com/vodaplayvietnam/vti-project-template
Project-URL: Repository, https://gitlab.com/vodaplayvietnam/vti-project-template
Keywords: toktak,utils,config,aws,ssm,secrets-manager
Classifier: Development Status :: 4 - Beta
Classifier: Intended Audience :: Developers
Classifier: Programming Language :: Python :: 3
Classifier: Programming Language :: Python :: 3.12
Classifier: Programming Language :: Python :: 3.13
Requires-Python: >=3.12
Requires-Dist: python-dotenv>=1.0.1
Requires-Dist: boto3>=1.42.5
Provides-Extra: dev
Requires-Dist: boto3-stubs[ssm]>=1.34.0; extra == "dev"
Requires-Dist: boto3-stubs[secretsmanager]>=1.34.0; extra == "dev"
Requires-Dist: boto3-stubs[stepfunctions]>=1.34.0; extra == "dev"
Provides-Extra: test
Requires-Dist: pytest>=8.0; extra == "test"
Requires-Dist: pytest-cov>=4.0.0; extra == "test"
Provides-Extra: linting
Requires-Dist: flake8>=7.0.0; extra == "linting"
Requires-Dist: flake8-bugbear>=24.0.0; extra == "linting"
Requires-Dist: mccabe>=0.7.0; extra == "linting"
Provides-Extra: security
Requires-Dist: bandit[toml]>=1.7.0; extra == "security"
Requires-Dist: pip-audit>=2.6.0; extra == "security"
